{
  "questions": {
    "1": { "answer1": { "scA": 1 }, "answer2": { "scC": 1 } },
    "2": { "answer1": { "scB": 1 }, "answer2": { "scA": 1 } },
    "3": { "answer1": { "scC": 1 }, "answer2": { "scA": 1 } },
    "4": { "answer1": { "scC": 1, "scD": 1 }, "answer2": { "scA": 1 } },
    "5": { "answer1": { "scB": 1 }, "answer2": { "scA": 1 } },
    "6": { "answer1": { "scA": 1 }, "answer2": { "scC": 1 } },
    "7": { "answer1": { "scC": 1 }, "answer2": { "scA": 1 } },
    "8": { "answer1": { "scB": 1 }, "answer2": { "scA": 1 } },
    "9": { "answer1": { "scA": 1 }, "answer2": { "scB": 1 } },
    "10": { "answer1": { "scC": 1 }, "answer2": { "scA": 1 } },
    "11": { "answer1": { "scB": 1, "scD": 1 }, "answer2": { "scA": 1 } },
    "12": { "answer1": { "scA": 1 }, "answer2": { "scD": 1 } },
    "13": { "answer1": { "scC": 1 }, "answer2": { "scA": 1 } },
    "14": { "answer1": { "scB": 1 }, "answer2": { "scA": 1 } },
    "15": { "answer1": { "scA": 1 }, "answer2": { "scB": 1 } },
    "16": { "answer1": { "scD": 1 }, "answer2": { "scA": 1 } },
    "17": { "answer1": { "scC": 1 }, "answer2": { "scA": 1 } },
    "18": { "answer1": { "scB": 1 }, "answer2": { "scA": 1 } },
    "19": { "answer1": { "scA": 1 }, "answer2": { "scD": 1 } },
    "20": { "answer1": { "scB": 1, "scD": 1 }, "answer2": { "scA": 1 } },
    "21": { "answer1": { "scB": 1 }, "answer2": { "scA": 1 } },
    "22": { "answer1": { "scA": 1 }, "answer2": { "scC": 1 } },
    "23": { "answer1": { "scC": 1 }, "answer2": { "scA": 1 } },
    "24": { "answer1": { "scB": 1 }, "answer2": { "scA": 1 } },
    "25": { "answer1": { "scA": 1 }, "answer2": { "scD": 1 } },
    "26": { "answer1": { "scC": 1 }, "answer2": { "scA": 1 } },
    "27": { "answer1": { "scB": 1, "scD": 1 }, "answer2": { "scA": 1 } },
    "28": { "answer1": { "scC": 1, "scD": 1 }, "answer2": { "scA": 1 } },
    "29": { "answer1": { "scA": 1 }, "answer2": { "scC": 1 } },
    "30": { "answer1": { "scB": 1, "scD": 1 }, "answer2": { "scA": 1 } },
    "31": { "answer1": { "scC": 1 }, "answer2": { "scA": 1 } },
    "32": { "answer1": { "scA": 1 }, "answer2": { "scB": 1 } },
    "33": { "answer1": { "scB": 1 }, "answer2": { "scA": 1 } },
    "34": { "answer1": { "scC": 1 }, "answer2": { "scA": 1 } },
    "35": { "answer1": { "scA": 1 }, "answer2": { "scD": 1 } },
    "36": { "answer1": { "scD": 1 }, "answer2": { "scA": 1 } },
    "37": { "answer1": { "scB": 1 }, "answer2": { "scA": 1 } },
    "38": { "answer1": { "scA": 1 }, "answer2": { "scC": 1 } },
    "39": { "answer1": { "scC": 1, "scD": 1 }, "answer2": { "scA": 1 } },
    "40": { "answer1": { "scB": 1 }, "answer2": { "scA": 1 } },
    "41": { "answer1": { "scA": 1 }, "answer2": { "scD": 1 } },
    "42": { "answer1": { "scB": 1, "scD": 1 }, "answer2": { "scA": 1 } },
    "43": { "answer1": { "scC": 1, "scD": 1 }, "answer2": { "scA": 1 } },
    "44": { "answer1": { "scA": 1 }, "answer2": { "scC": 1 } },
    "45": { "answer1": { "scB": 1, "scD": 1 }, "answer2": { "scA": 1 } }
  }
}

